<?xml version="1.0" encoding="UTF-8" ?>
<suite name="自定义接口测试套件">
    <test name="测试报告">
        <classes>
            <class name="com.course.code.TestMethodsDemo">
                <methods>
                    <include name="test1"/>
                    <include name="test2"/>
                    <include name="test3"/>
                    <include name="logDemo"/>
                </methods>
            </class>
        </classes>
    </test>
<!--    配置监听器，监听测试报告-->
    <listeners>
<!--        <listener class-name="com.vimalselvam.testng.listener.ExtentTestNgFormatter"/>-->
        <listener class-name="com.course.code.ExtentTestNGIReporterListener"/>
    </listeners>
</suite>